rhotermpredict/__init__.py
rhotermpredict/algorithm.py
rhotermpredict-3.4.dist-info/LICENSE
rhotermpredict-3.4.dist-info/METADATA
rhotermpredict-3.4.dist-info/WHEEL
rhotermpredict-3.4.dist-info/entry_points.txt
rhotermpredict-3.4.dist-info/top_level.txt
rhotermpredict-3.4.dist-info/RECORD
