Metadata-Version: 2.1
Name: rhotermpredict
Version: 3.4
Summary: RhoTermPredict (Barrick Lab Fork)
Home-page: https://github.com/barricklab/RhoTermPredict
Author: Cameron Roots
Author-email: croots@utexas.edu
Project-URL: Bug Tracker, https://github.com/barricklab/RhoTermPredict/issues
Project-URL: Source Code, https://github.com/barricklab/RhoTermPredict
Classifier: License :: OSI Approved :: GNU Affero General Public License v3
License-File: LICENSE
Requires-Dist: numpy >=1.15.4
Requires-Dist: biopython >=0.1.0
